pauliopt/__init__.py
pauliopt/qasm.py
pauliopt/topologies.py
pauliopt/utils.py
pauliopt/pauli/__init__.py
pauliopt/phase/__init__.py
pauliopt/phase/circuits.py
pauliopt/phase/cx_circuits.py
pauliopt/phase/optimized_circuits.py
pauliopt/phase/optimizers.py
pauliopt/phase/phase_circuits.py
pauliopt-0.0.4.post1.dist-info/LICENSE
pauliopt-0.0.4.post1.dist-info/METADATA
pauliopt-0.0.4.post1.dist-info/WHEEL
pauliopt-0.0.4.post1.dist-info/top_level.txt
pauliopt-0.0.4.post1.dist-info/RECORD
