Metadata-Version: 2.1
Name: pauliopt
Version: 0.0.4.post1
Summary: A Python library to simplify quantum circuits of Pauli gadgets.
Home-page: https://github.com/sg495/pauliopt
Maintainer: sg495
Maintainer-email: sg495@users.noreply.github.com
License: UNKNOWN
Platform: UNKNOWN
Classifier: Programming Language :: Python :: 3.8
Classifier: Operating System :: OS Independent
Classifier: Development Status :: 2 - Pre-Alpha
Classifier: Natural Language :: English
Classifier: Typing :: Typed
Requires-Dist: numpy
